api_client/__init__.py
api_client/api.py
api_client/client.py
api_client/settings.py
pythonista_api_client-0.1.4.dist-info/METADATA
pythonista_api_client-0.1.4.dist-info/RECORD
pythonista_api_client-0.1.4.dist-info/WHEEL
pythonista_api_client-0.1.4.dist-info/top_level.txt
