Metadata-Version: 2.1
Name: pythonista-api-client
Version: 0.1.4
Summary: Making requests to rest apis in pythonista.
Home-page: https://github.com/ephes/pythonista_api_client
Author: Jochen Wersdoerfer
Author-email: jochen-pythonista@wersdoerfer.de
License: UNKNOWN
Keywords: api rest pythonista jwt token drf
Platform: UNKNOWN
Classifier: Development Status :: 3 - Alpha
Classifier: Intended Audience :: Developers
Classifier: Topic :: Internet :: WWW/HTTP
Classifier: License :: OSI Approved :: MIT License
Classifier: Programming Language :: Python :: 3.6
Provides-Extra: dev
Requires-Dist: requests
Provides-Extra: dev
Requires-Dist: pytest; extra == 'dev'
Requires-Dist: flake8; extra == 'dev'
